{
  "shortname": "18708",
  "longname": "18708, USA",
  "source": "Census",
  "rows": [
    {
      "statname": "Population",
      "statval": 8938.0,
      "ordinal": 10379,
      "total_in_class": 32967,
      "row_type": "ZIP",
      "ba_within_type": [
        "20695, USA",
        "25560, USA"
      ],
      "ba_overall": [
        "20695, USA",
        "49038, USA"
      ]
    },
    {
      "statname": "PW Density (r=1km)",
      "statval": 359.4063705952245,
      "ordinal": 11103,
      "total_in_class": 32967,
      "row_type": "ZIP",
      "ba_within_type": [
        "97396, USA",
        "62930, USA"
      ],
      "ba_overall": [
        "97396, USA",
        "62930, USA"
      ]
    },
    {
      "statname": "AW Density",
      "statval": 207.59984247973856,
      "ordinal": 8966,
      "total_in_class": 32967,
      "row_type": "ZIP",
      "ba_within_type": [
        "48356, USA",
        "16001, USA"
      ],
      "ba_overall": [
        "Millfield CDP, Ohio, USA",
        "Beaver city, Utah, USA"
      ]
    },
    {
      "statname": "White %",
      "statval": 0.9452897739986574,
      "ordinal": 4010,
      "total_in_class": 32967,
      "row_type": "ZIP",
      "ba_within_type": [
        "54950, USA",
        "62380, USA"
      ],
      "ba_overall": [
        "54950, USA",
        "62380, USA"
      ]
    },
    {
      "statname": "Hispanic %",
      "statval": 0.012530767509509957,
      "ordinal": 28090,
      "total_in_class": 32967,
      "row_type": "ZIP",
      "ba_within_type": [
        "16947, USA",
        "13438, USA"
      ],
      "ba_overall": [
        "Shuqualak town, Mississippi, USA",
        "13438, USA"
      ]
    },
    {
      "statname": "Black %",
      "statval": 0.003356455582904453,
      "ordinal": 23509,
      "total_in_class": 32967,
      "row_type": "ZIP",
      "ba_within_type": [
        "97385, USA",
        "83448, USA"
      ],
      "ba_overall": [
        "97385, USA",
        "Keene township [CCD], Adams County, Illinois, USA"
      ]
    },
    {
      "statname": "Asian %",
      "statval": 0.012530767509509957,
      "ordinal": 9950,
      "total_in_class": 32967,
      "row_type": "ZIP",
      "ba_within_type": [
        "19945, USA",
        "48122, USA"
      ],
      "ba_overall": [
        "19945, USA",
        "East Allentown Neighborhood, Allentown City, Pennsylvania, USA"
      ]
    },
    {
      "statname": "Native %",
      "statval": 0.0003356455582904453,
      "ordinal": 26888,
      "total_in_class": 32967,
      "row_type": "ZIP",
      "ba_within_type": [
        "06455, USA",
        "12074, USA"
      ],
      "ba_overall": [
        "06455, USA",
        "Sharon township [CCD], Medina County, Ohio, USA"
      ]
    },
    {
      "statname": "Hawaiian / PI %",
      "statval": 0.0,
      "ordinal": 24526,
      "total_in_class": 32967,
      "row_type": "ZIP",
      "ba_within_type": [
        "24266, USA",
        "04915, USA"
      ],
      "ba_overall": [
        "Piedmont CDP, South Carolina, USA",
        "Twin Lake township [CCD], Benson County, North Dakota, USA"
      ]
    },
    {
      "statname": "Other / Mixed %",
      "statval": 0.02595658984112777,
      "ordinal": 26320,
      "total_in_class": 32967,
      "row_type": "ZIP",
      "ba_within_type": [
        "11741, USA",
        "31070, USA"
      ],
      "ba_overall": [
        "11741, USA",
        "31070, USA"
      ]
    },
    {
      "statname": "Housing Units per Adult",
      "statval": 0.5278195488721804,
      "ordinal": 24397,
      "total_in_class": 32967,
      "row_type": "ZIP",
      "ba_within_type": [
        "73106, USA",
        "14072, USA"
      ],
      "ba_overall": [
        "Lake Hollingsworth Neighborhood, Lakeland City, Florida, USA",
        "Upper Clinton Hill Neighborhood, Newark City, New Jersey, USA"
      ]
    },
    {
      "statname": "Vacancy %",
      "statval": 0.04428904428904429,
      "ordinal": 28813,
      "total_in_class": 32967,
      "row_type": "ZIP",
      "ba_within_type": [
        "43221, USA",
        "55116, USA"
      ],
      "ba_overall": [
        "Lake Success village, New York, USA",
        "55116, USA"
      ]
    },
    {
      "statname": "2020 Presidential Election",
      "statval": -0.17948129352603695,
      "ordinal": 13132,
      "total_in_class": 32967,
      "row_type": "ZIP",
      "ba_within_type": [
        "92305, USA",
        "95531, USA"
      ],
      "ba_overall": [
        "Great Bridge Neighborhood, Chesapeake City, Virginia, USA",
        "95531, USA"
      ]
    },
    {
      "statname": "2016 Presidential Election",
      "statval": -0.25541644527601987,
      "ordinal": 14612,
      "total_in_class": 32967,
      "row_type": "ZIP",
      "ba_within_type": [
        "44907, USA",
        "87832, USA"
      ],
      "ba_overall": [
        "Shelbyville CCD [CCD], Shelby County, Kentucky, USA",
        "North Vandergrift CDP, Pennsylvania, USA"
      ]
    },
    {
      "statname": "PW Density (r=250m)",
      "statval": 945.7711088970742,
      "ordinal": 12116,
      "total_in_class": 32967,
      "row_type": "ZIP",
      "ba_within_type": [
        "75943, USA",
        "40769, USA"
      ],
      "ba_overall": [
        "75943, USA",
        "40769, USA"
      ]
    },
    {
      "statname": "PW Density (r=500m)",
      "statval": 452.88224608970336,
      "ordinal": 12547,
      "total_in_class": 32967,
      "row_type": "ZIP",
      "ba_within_type": [
        "68978, USA",
        "66032, USA"
      ],
      "ba_overall": [
        "Whittemore city, Iowa, USA",
        "66032, USA"
      ]
    },
    {
      "statname": "PW Density (r=2km)",
      "statval": 297.5803109770695,
      "ordinal": 10113,
      "total_in_class": 32967,
      "row_type": "ZIP",
      "ba_within_type": [
        "15007, USA",
        "75455, USA"
      ],
      "ba_overall": [
        "Jacobus borough [CCD], York County, Pennsylvania, USA",
        "Wahoo city, Nebraska, USA"
      ]
    },
    {
      "statname": "PW Density (r=4km)",
      "statval": 241.89317073118187,
      "ordinal": 9487,
      "total_in_class": 32967,
      "row_type": "ZIP",
      "ba_within_type": [
        "30252, USA",
        "74003, USA"
      ],
      "ba_overall": [
        "30252, USA",
        "Charleston-Huntington-Ashland CSA, WV-OH-KY, USA"
      ]
    }
  ],
  "related": {
    "contains": [
      {
        "longname": "Chase CDP, Pennsylvania, USA",
        "shortname": "Chase CDP",
        "row_type": "City"
      },
      {
        "longname": "Shavertown CDP, Pennsylvania, USA",
        "shortname": "Shavertown CDP",
        "row_type": "City"
      },
      {
        "longname": "Trucksville CDP, Pennsylvania, USA",
        "shortname": "Trucksville CDP",
        "row_type": "City"
      }
    ],
    "contained_by": [],
    "intersects": [],
    "borders": [
      {
        "longname": "18612, USA",
        "shortname": "18612",
        "row_type": "ZIP"
      },
      {
        "longname": "18621, USA",
        "shortname": "18621",
        "row_type": "ZIP"
      },
      {
        "longname": "18644, USA",
        "shortname": "18644",
        "row_type": "ZIP"
      },
      {
        "longname": "18651, USA",
        "shortname": "18651",
        "row_type": "ZIP"
      },
      {
        "longname": "18704, USA",
        "shortname": "18704",
        "row_type": "ZIP"
      }
    ]
  }
}