{
  "shortname": "18980",
  "longname": "18980, USA",
  "source": "Census",
  "rows": [
    {
      "statname": "Population",
      "statval": 540.0,
      "ordinal": 26105,
      "total_in_class": 32967,
      "row_type": "ZIP",
      "ba_within_type": [
        "80481, USA",
        "24726, USA"
      ],
      "ba_overall": [
        "Marshall town [CCD], Richland County, Wisconsin, USA",
        "West Wildwood borough [CCD], Cape May County, New Jersey, USA"
      ]
    },
    {
      "statname": "PW Density (r=1km)",
      "statval": 95.13869874106969,
      "ordinal": 19188,
      "total_in_class": 32967,
      "row_type": "ZIP",
      "ba_within_type": [
        "97462, USA",
        "14441, USA"
      ],
      "ba_overall": [
        "Bourbon township [CCD], Boone County, Missouri, USA",
        "Northampton County, Virginia, USA"
      ]
    },
    {
      "statname": "AW Density",
      "statval": 87.13585201640666,
      "ordinal": 11876,
      "total_in_class": 32967,
      "row_type": "ZIP",
      "ba_within_type": [
        "30529, USA",
        "44272, USA"
      ],
      "ba_overall": [
        "Jupiter Island town, Florida, USA",
        "44272, USA"
      ]
    },
    {
      "statname": "White %",
      "statval": 0.8351851851851851,
      "ordinal": 16665,
      "total_in_class": 32967,
      "row_type": "ZIP",
      "ba_within_type": [
        "21631, USA",
        "99714, USA"
      ],
      "ba_overall": [
        "Cloverdale CDP, Virginia, USA",
        "Pamelia town [CCD], Jefferson County, New York, USA"
      ]
    },
    {
      "statname": "Hispanic %",
      "statval": 0.040740740740740744,
      "ordinal": 16578,
      "total_in_class": 32967,
      "row_type": "ZIP",
      "ba_within_type": [
        "05405, USA",
        "56304, USA"
      ],
      "ba_overall": [
        "Rudyard CDP, Montana, USA",
        "District 1 [CCD], Bossier Parish, Louisiana, USA"
      ]
    },
    {
      "statname": "Black %",
      "statval": 0.024074074074074074,
      "ordinal": 12310,
      "total_in_class": 32967,
      "row_type": "ZIP",
      "ba_within_type": [
        "67005, USA",
        "61008, USA"
      ],
      "ba_overall": [
        "67005, USA",
        "Weyers Cave CDP, Virginia, USA"
      ]
    },
    {
      "statname": "Asian %",
      "statval": 0.022222222222222223,
      "ordinal": 7016,
      "total_in_class": 32967,
      "row_type": "ZIP",
      "ba_within_type": [
        "93627, USA",
        "84041, USA"
      ],
      "ba_overall": [
        "93554, USA",
        "87554, USA"
      ]
    },
    {
      "statname": "Native %",
      "statval": 0.0,
      "ordinal": 30138,
      "total_in_class": 32967,
      "row_type": "ZIP",
      "ba_within_type": [
        "24726, USA",
        "41159, USA"
      ],
      "ba_overall": [
        "Great Neck Gardens Neighborhood, Great Neck City, New York, USA",
        "Lanare CDP, California, USA"
      ]
    },
    {
      "statname": "Hawaiian / PI %",
      "statval": 0.0,
      "ordinal": 24526,
      "total_in_class": 32967,
      "row_type": "ZIP",
      "ba_within_type": [
        "24873, USA",
        "37333, USA"
      ],
      "ba_overall": [
        "Lanare CDP, California, USA",
        "Pike township [CCD], Livingston County, Illinois, USA"
      ]
    },
    {
      "statname": "Other / Mixed %",
      "statval": 0.07777777777777778,
      "ordinal": 2104,
      "total_in_class": 32967,
      "row_type": "ZIP",
      "ba_within_type": [
        "96040, USA",
        "64101, USA"
      ],
      "ba_overall": [
        "Rockport CDP, Washington, USA",
        "Hindsville town, Arkansas, USA"
      ]
    },
    {
      "statname": "Housing Units per Adult",
      "statval": 0.46444444444444444,
      "ordinal": 30267,
      "total_in_class": 32967,
      "row_type": "ZIP",
      "ba_within_type": [
        "02459, USA",
        "75098, USA"
      ],
      "ba_overall": [
        "Marriott-Slaterville city, Utah, USA",
        "75098, USA"
      ]
    },
    {
      "statname": "Vacancy %",
      "statval": 0.09090909090909091,
      "ordinal": 19634,
      "total_in_class": 32967,
      "row_type": "ZIP",
      "ba_within_type": [
        "59485, USA",
        "93608, USA"
      ],
      "ba_overall": [
        "74640, USA",
        "Rosedale township [CCD], Tripp County, South Dakota, USA"
      ]
    },
    {
      "statname": "2020 Presidential Election",
      "statval": -0.07036880033912674,
      "ordinal": 10711,
      "total_in_class": 32967,
      "row_type": "ZIP",
      "ba_within_type": [
        "56637, USA",
        "35756, USA"
      ],
      "ba_overall": [
        "Laflin borough [CCD], Luzerne County, Pennsylvania, USA",
        "Wrightstown township [CCD], Bucks County, Pennsylvania, USA"
      ]
    },
    {
      "statname": "2016 Presidential Election",
      "statval": -0.09902011346054669,
      "ordinal": 10505,
      "total_in_class": 32967,
      "row_type": "ZIP",
      "ba_within_type": [
        "02822, USA",
        "04345, USA"
      ],
      "ba_overall": [
        "Wrightstown township [CCD], Bucks County, Pennsylvania, USA",
        "04345, USA"
      ]
    },
    {
      "statname": "PW Density (r=250m)",
      "statval": 555.1701671206713,
      "ordinal": 16782,
      "total_in_class": 32967,
      "row_type": "ZIP",
      "ba_within_type": [
        "46923, USA",
        "15422, USA"
      ],
      "ba_overall": [
        "Washington township [CCD], Pike County, Indiana, USA",
        "Kittitas CCD [CCD], Kittitas County, Washington, USA"
      ]
    },
    {
      "statname": "PW Density (r=500m)",
      "statval": 183.16729776519702,
      "ordinal": 19607,
      "total_in_class": 32967,
      "row_type": "ZIP",
      "ba_within_type": [
        "87043, USA",
        "61724, USA"
      ],
      "ba_overall": [
        "Saratoga town, North Carolina, USA",
        "Chatfield village, Ohio, USA"
      ]
    },
    {
      "statname": "PW Density (r=2km)",
      "statval": 117.57541947776159,
      "ordinal": 14211,
      "total_in_class": 32967,
      "row_type": "ZIP",
      "ba_within_type": [
        "43734, USA",
        "62411, USA"
      ],
      "ba_overall": [
        "Bourbon city, Missouri, USA",
        "Kendall CDP, Washington, USA"
      ]
    },
    {
      "statname": "PW Density (r=4km)",
      "statval": 137.3115166152849,
      "ordinal": 11499,
      "total_in_class": 32967,
      "row_type": "ZIP",
      "ba_within_type": [
        "74361, USA",
        "69001, USA"
      ],
      "ba_overall": [
        "74361, USA",
        "69001, USA"
      ]
    }
  ],
  "related": {
    "contains": [],
    "contained_by": [
      {
        "longname": "Wrightstown township [CCD], Bucks County, Pennsylvania, USA",
        "shortname": "Wrightstown township",
        "row_type": "CCD"
      }
    ],
    "intersects": [],
    "borders": [
      {
        "longname": "18925, USA",
        "shortname": "18925",
        "row_type": "ZIP"
      },
      {
        "longname": "18929, USA",
        "shortname": "18929",
        "row_type": "ZIP"
      },
      {
        "longname": "18940, USA",
        "shortname": "18940",
        "row_type": "ZIP"
      },
      {
        "longname": "18974, USA",
        "shortname": "18974",
        "row_type": "ZIP"
      }
    ]
  }
}