{
  "shortname": "29829",
  "longname": "29829, USA",
  "source": "Census",
  "rows": [
    {
      "statname": "Population",
      "statval": 12561.0,
      "ordinal": 8738,
      "total_in_class": 32967,
      "row_type": "ZIP",
      "ba_within_type": [
        "40336, USA",
        "11764, USA"
      ],
      "ba_overall": [
        "Eastmoor Neighborhood, Columbus City, Ohio, USA",
        "11764, USA"
      ]
    },
    {
      "statname": "PW Density (r=1km)",
      "statval": 356.6365910218479,
      "ordinal": 11154,
      "total_in_class": 32967,
      "row_type": "ZIP",
      "ba_within_type": [
        "12549, USA",
        "19465, USA"
      ],
      "ba_overall": [
        "Historical Congressional District IL-22, 98th-102nd Congress, USA",
        "Suffield School District, Connecticut, USA"
      ]
    },
    {
      "statname": "AW Density",
      "statval": 145.66621786198868,
      "ordinal": 10062,
      "total_in_class": 32967,
      "row_type": "ZIP",
      "ba_within_type": [
        "21048, USA",
        "49684, USA"
      ],
      "ba_overall": [
        "21048, USA",
        "Potterville Public Schools, Michigan, USA"
      ]
    },
    {
      "statname": "White %",
      "statval": 0.5868959477748587,
      "ordinal": 25708,
      "total_in_class": 32967,
      "row_type": "ZIP",
      "ba_within_type": [
        "31525, USA",
        "85603, USA"
      ],
      "ba_overall": [
        "CO-HD030, USA",
        "Eden Consolidated Independent School District, Texas, USA"
      ]
    },
    {
      "statname": "Hispanic %",
      "statval": 0.0890056524162089,
      "ordinal": 9585,
      "total_in_class": 32967,
      "row_type": "ZIP",
      "ba_within_type": [
        "79091, USA",
        "94960, USA"
      ],
      "ba_overall": [
        "Wofford Heights CDP, California, USA",
        "Paauilo CDP, Hawaii, USA"
      ]
    },
    {
      "statname": "Black %",
      "statval": 0.2631956054454263,
      "ordinal": 2845,
      "total_in_class": 32967,
      "row_type": "ZIP",
      "ba_within_type": [
        "71277, USA",
        "35811, USA"
      ],
      "ba_overall": [
        "AR-HD061, USA",
        "Riverfront Neighborhood, Waterloo City, Iowa, USA"
      ]
    },
    {
      "statname": "Asian %",
      "statval": 0.010429105962901043,
      "ordinal": 11093,
      "total_in_class": 32967,
      "row_type": "ZIP",
      "ba_within_type": [
        "91934, USA",
        "90303, USA"
      ],
      "ba_overall": [
        "Somerset Unorganized Territory, Maine, USA",
        "Birchwood Village city, Minnesota, USA"
      ]
    },
    {
      "statname": "Native %",
      "statval": 0.0035029058196003504,
      "ordinal": 11595,
      "total_in_class": 32967,
      "row_type": "ZIP",
      "ba_within_type": [
        "37042, USA",
        "36264, USA"
      ],
      "ba_overall": [
        "West Tom Green CCD [CCD], Tom Green County, Texas, USA",
        "Historical Congressional District TX-6, 108th Congress, USA"
      ]
    },
    {
      "statname": "Hawaiian / PI %",
      "statval": 0.0007961149590000797,
      "ordinal": 6155,
      "total_in_class": 32967,
      "row_type": "ZIP",
      "ba_within_type": [
        "81004, USA",
        "22303, USA"
      ],
      "ba_overall": [
        "81004, USA",
        "District 14 [CCD], Rutherford County, Tennessee, USA"
      ]
    },
    {
      "statname": "Other / Mixed %",
      "statval": 0.04617466762200462,
      "ordinal": 11566,
      "total_in_class": 32967,
      "row_type": "ZIP",
      "ba_within_type": [
        "46368, USA",
        "48827, USA"
      ],
      "ba_overall": [
        "46368, USA",
        "WY-SD012, USA"
      ]
    },
    {
      "statname": "Housing Units per Adult",
      "statval": 0.5400779896013865,
      "ordinal": 22551,
      "total_in_class": 32967,
      "row_type": "ZIP",
      "ba_within_type": [
        "31771, USA",
        "17981, USA"
      ],
      "ba_overall": [
        "Historical Congressional District CT-1, 73rd-88th Congress, USA",
        "67860, USA"
      ]
    },
    {
      "statname": "Vacancy %",
      "statval": 0.08403529883674288,
      "ordinal": 20811,
      "total_in_class": 32967,
      "row_type": "ZIP",
      "ba_within_type": [
        "47501, USA",
        "15676, USA"
      ],
      "ba_overall": [
        "Read Blvd. West Neighborhood, New Orleans City, Louisiana, USA",
        "Pleasant Valley township [CCD], Johnson County, Iowa, USA"
      ]
    },
    {
      "statname": "2020 Presidential Election",
      "statval": -0.255164262324427,
      "ordinal": 15060,
      "total_in_class": 32967,
      "row_type": "ZIP",
      "ba_within_type": [
        "60081, USA",
        "12422, USA"
      ],
      "ba_overall": [
        "Beaver Creek township [CCD], Steele County, North Dakota, USA",
        "Farm Island township [CCD], Aitkin County, Minnesota, USA"
      ]
    },
    {
      "statname": "2016 Presidential Election",
      "statval": -0.34783484876792375,
      "ordinal": 17607,
      "total_in_class": 32967,
      "row_type": "ZIP",
      "ba_within_type": [
        "52215, USA",
        "83867, USA"
      ],
      "ba_overall": [
        "Sterling Ridge Neighborhood, The Woodlands City, Texas, USA",
        "83867, USA"
      ]
    },
    {
      "statname": "PW Density (r=250m)",
      "statval": 1786.6503560659025,
      "ordinal": 7422,
      "total_in_class": 32967,
      "row_type": "ZIP",
      "ba_within_type": [
        "34945, USA",
        "61108, USA"
      ],
      "ba_overall": [
        "Springfield R-XII School District, Missouri, USA",
        "New Providence borough [CCD], Union County, New Jersey, USA"
      ]
    },
    {
      "statname": "PW Density (r=500m)",
      "statval": 734.3817826625639,
      "ordinal": 9477,
      "total_in_class": 32967,
      "row_type": "ZIP",
      "ba_within_type": [
        "44256, USA",
        "06840, USA"
      ],
      "ba_overall": [
        "Riddle city, Oregon, USA",
        "KY-HD058, USA"
      ]
    },
    {
      "statname": "PW Density (r=2km)",
      "statval": 194.72914548448557,
      "ordinal": 11861,
      "total_in_class": 32967,
      "row_type": "ZIP",
      "ba_within_type": [
        "98532, USA",
        "29571, USA"
      ],
      "ba_overall": [
        "Caguabo barrio [CCD], A\u00f1asco Municipio, Puerto Rico, USA",
        "Darlington CCD [CCD], Darlington County, South Carolina, USA"
      ]
    },
    {
      "statname": "PW Density (r=4km)",
      "statval": 186.2420538800045,
      "ordinal": 10363,
      "total_in_class": 32967,
      "row_type": "ZIP",
      "ba_within_type": [
        "23909, USA",
        "28711, USA"
      ],
      "ba_overall": [
        "Clarksdale MSA, MS, USA",
        "Big Prairie township [CCD], New Madrid County, Missouri, USA"
      ]
    }
  ],
  "related": {
    "same_geography": [],
    "contained_by": [
      {
        "longname": "South Carolina, USA",
        "shortname": "South Carolina",
        "row_type": "State"
      },
      {
        "longname": "Augusta-Richmond County MSA, GA-SC, USA",
        "shortname": "Augusta-Richmond County MSA",
        "row_type": "MSA"
      },
      {
        "longname": "Aiken County, South Carolina, USA",
        "shortname": "Aiken County",
        "row_type": "County"
      },
      {
        "longname": "Historical Congressional District SC-2, 113th-117th Congress, USA",
        "shortname": "SC-02 [113th-117th Congress]",
        "row_type": "Historical Congressional District"
      },
      {
        "longname": "Historical Congressional District SC-3, 108th-112th Congress, USA",
        "shortname": "SC-03 [108th-112th Congress]",
        "row_type": "Historical Congressional District"
      },
      {
        "longname": "Historical Congressional District SC-3, 104th-107th Congress, USA",
        "shortname": "SC-03 [104th-107th Congress]",
        "row_type": "Historical Congressional District"
      },
      {
        "longname": "Historical Congressional District SC-3, 103rd Congress, USA",
        "shortname": "SC-03 [103rd Congress]",
        "row_type": "Historical Congressional District"
      },
      {
        "longname": "Historical Congressional District SC-3, 98th-102nd Congress, USA",
        "shortname": "SC-03 [98th-102nd Congress]",
        "row_type": "Historical Congressional District"
      },
      {
        "longname": "Historical Congressional District SC-3, 93rd-97th Congress, USA",
        "shortname": "SC-03 [93rd-97th Congress]",
        "row_type": "Historical Congressional District"
      },
      {
        "longname": "Historical Congressional District SC-3, 90th-92nd Congress, USA",
        "shortname": "SC-03 [90th-92nd Congress]",
        "row_type": "Historical Congressional District"
      },
      {
        "longname": "Historical Congressional District SC-2, 89th Congress, USA",
        "shortname": "SC-02 [89th Congress]",
        "row_type": "Historical Congressional District"
      },
      {
        "longname": "Historical Congressional District SC-2, 73rd-88th Congress, USA",
        "shortname": "SC-02 [73rd-88th Congress]",
        "row_type": "Historical Congressional District"
      },
      {
        "longname": "Historical Congressional District SC-2, 65th-72nd Congress, USA",
        "shortname": "SC-02 [65th-72nd Congress]",
        "row_type": "Historical Congressional District"
      },
      {
        "longname": "Historical Congressional District SC-2, 58th-64th Congress, USA",
        "shortname": "SC-02 [58th-64th Congress]",
        "row_type": "Historical Congressional District"
      },
      {
        "longname": "Historical Congressional District SC-2, 56th-57th Congress, USA",
        "shortname": "SC-02 [56th-57th Congress]",
        "row_type": "Historical Congressional District"
      },
      {
        "longname": "Historical Congressional District SC-2, 54th-55th Congress, USA",
        "shortname": "SC-02 [54th-55th Congress]",
        "row_type": "Historical Congressional District"
      },
      {
        "longname": "Historical Congressional District SC-2, 48th-53rd Congress, USA",
        "shortname": "SC-02 [48th-53rd Congress]",
        "row_type": "Historical Congressional District"
      },
      {
        "longname": "Historical Congressional District SC-5, 45th-47th Congress, USA",
        "shortname": "SC-05 [45th-47th Congress]",
        "row_type": "Historical Congressional District"
      },
      {
        "longname": "Historical Congressional District SC-5, 44th Congress, USA",
        "shortname": "SC-05 [44th Congress]",
        "row_type": "Historical Congressional District"
      },
      {
        "longname": "Historical Congressional District SC-3, 43rd Congress, USA",
        "shortname": "SC-03 [43rd Congress]",
        "row_type": "Historical Congressional District"
      },
      {
        "longname": "Historical Congressional District SC-3, 40th-42nd Congress, USA",
        "shortname": "SC-03 [40th-42nd Congress]",
        "row_type": "Historical Congressional District"
      },
      {
        "longname": "Historical Congressional District SC-4, 33rd-36th Congress, USA",
        "shortname": "SC-04 [33rd-36th Congress]",
        "row_type": "Historical Congressional District"
      },
      {
        "longname": "Historical Congressional District SC-5, 28th-32nd Congress, USA",
        "shortname": "SC-05 [28th-32nd Congress]",
        "row_type": "Historical Congressional District"
      },
      {
        "longname": "Historical Congressional District SC-5, 18th-27th Congress, USA",
        "shortname": "SC-05 [18th-27th Congress]",
        "row_type": "Historical Congressional District"
      },
      {
        "longname": "Historical Congressional District SC-6, 15th-17th Congress, USA",
        "shortname": "SC-06 [15th-17th Congress]",
        "row_type": "Historical Congressional District"
      },
      {
        "longname": "Historical Congressional District SC-6, 13th-14th Congress, USA",
        "shortname": "SC-06 [13th-14th Congress]",
        "row_type": "Historical Congressional District"
      },
      {
        "longname": "Historical Congressional District SC-2, 8th-12th Congress, USA",
        "shortname": "SC-02 [8th-12th Congress]",
        "row_type": "Historical Congressional District"
      },
      {
        "longname": "Historical Congressional District SC-5, 3rd-7th Congress, USA",
        "shortname": "SC-05 [3rd-7th Congress]",
        "row_type": "Historical Congressional District"
      },
      {
        "longname": "Historical Congressional District SC-5, 1st-2nd Congress, USA",
        "shortname": "SC-05 [1st-2nd Congress]",
        "row_type": "Historical Congressional District"
      },
      {
        "longname": "SC-SD025, USA",
        "shortname": "SC-SD025",
        "row_type": "State Senate District"
      },
      {
        "longname": "SC-02, USA",
        "shortname": "SC-02",
        "row_type": "Congressional District"
      },
      {
        "longname": "Aiken County School District, South Carolina, USA",
        "shortname": "Aiken County School District",
        "row_type": "School District"
      }
    ],
    "contains": [],
    "borders": [
      {
        "longname": "29801, USA",
        "shortname": "29801",
        "row_type": "ZIP"
      },
      {
        "longname": "29834, USA",
        "shortname": "29834",
        "row_type": "ZIP"
      },
      {
        "longname": "29841, USA",
        "shortname": "29841",
        "row_type": "ZIP"
      },
      {
        "longname": "29842, USA",
        "shortname": "29842",
        "row_type": "ZIP"
      },
      {
        "longname": "29847, USA",
        "shortname": "29847",
        "row_type": "ZIP"
      },
      {
        "longname": "29850, USA",
        "shortname": "29850",
        "row_type": "ZIP"
      },
      {
        "longname": "29851, USA",
        "shortname": "29851",
        "row_type": "ZIP"
      },
      {
        "longname": "29860, USA",
        "shortname": "29860",
        "row_type": "ZIP"
      }
    ],
    "intersects": [
      {
        "longname": "SC-HD082, USA",
        "shortname": "SC-HD082",
        "row_type": "State House District"
      },
      {
        "longname": "SC-HD084, USA",
        "shortname": "SC-HD084",
        "row_type": "State House District"
      },
      {
        "longname": "Aiken CCD [CCD], Aiken County, South Carolina, USA",
        "shortname": "Aiken CCD",
        "row_type": "CCD"
      },
      {
        "longname": "North Augusta CCD [CCD], Aiken County, South Carolina, USA",
        "shortname": "North Augusta CCD",
        "row_type": "CCD"
      },
      {
        "longname": "Burnettown town, South Carolina, USA",
        "shortname": "Burnettown town",
        "row_type": "City"
      },
      {
        "longname": "Graniteville CDP, South Carolina, USA",
        "shortname": "Graniteville CDP",
        "row_type": "City"
      }
    ]
  }
}