{
  "shortname": "43117",
  "longname": "43117, USA",
  "source": "Census",
  "rows": [
    {
      "statname": "Population",
      "statval": 33.0,
      "ordinal": 32654,
      "total_in_class": 32967,
      "row_type": "ZIP",
      "ba_within_type": [
        "38077, USA",
        "88421, USA"
      ],
      "ba_overall": [
        "Raber township [CCD], Hughes County, South Dakota, USA",
        "Hollister town, Oklahoma, USA"
      ]
    },
    {
      "statname": "PW Density (r=1km)",
      "statval": 89.4933067882791,
      "ordinal": 19573,
      "total_in_class": 32967,
      "row_type": "ZIP",
      "ba_within_type": [
        "62628, USA",
        "50071, USA"
      ],
      "ba_overall": [
        "Kilbourne village, Louisiana, USA",
        "Osino CDP, Nevada, USA"
      ]
    },
    {
      "statname": "AW Density",
      "statval": 776.1333839486468,
      "ordinal": 4940,
      "total_in_class": 32967,
      "row_type": "ZIP",
      "ba_within_type": [
        "61704, USA",
        "89011, USA"
      ],
      "ba_overall": [
        "61704, USA",
        "Madison CCD [CCD], Madison County, Alabama, USA"
      ]
    },
    {
      "statname": "White %",
      "statval": 0.7878787878787878,
      "ordinal": 19182,
      "total_in_class": 32967,
      "row_type": "ZIP",
      "ba_within_type": [
        "84405, USA",
        "55720, USA"
      ],
      "ba_overall": [
        "Raber township [CCD], Hughes County, South Dakota, USA",
        "Arvada CDP, Wyoming, USA"
      ]
    },
    {
      "statname": "Hispanic %",
      "statval": 0.0,
      "ordinal": 32559,
      "total_in_class": 32967,
      "row_type": "ZIP",
      "ba_within_type": [
        "13064, USA",
        "58323, USA"
      ],
      "ba_overall": [
        "Chain Lakes township [CCD], Ramsey County, North Dakota, USA",
        "Sibley Butte township [CCD], Burleigh County, North Dakota, USA"
      ]
    },
    {
      "statname": "Black %",
      "statval": 0.0,
      "ordinal": 30674,
      "total_in_class": 32967,
      "row_type": "ZIP",
      "ba_within_type": [
        "38077, USA",
        "80434, USA"
      ],
      "ba_overall": [
        "Moore township [CCD], Barber County, Kansas, USA",
        "99569, USA"
      ]
    },
    {
      "statname": "Asian %",
      "statval": 0.030303030303030304,
      "ordinal": 5641,
      "total_in_class": 32967,
      "row_type": "ZIP",
      "ba_within_type": [
        "32669, USA",
        "90090, USA"
      ],
      "ba_overall": [
        "Towne Lake Garden Neighborhood, San Antonio City, Texas, USA",
        "Loomis CDP, South Dakota, USA"
      ]
    },
    {
      "statname": "Native %",
      "statval": 0.030303030303030304,
      "ordinal": 1887,
      "total_in_class": 32967,
      "row_type": "ZIP",
      "ba_within_type": [
        "54561, USA",
        "38077, USA"
      ],
      "ba_overall": [
        "Lake Flat township [CCD], Pennington County, South Dakota, USA",
        "Hollister town, Oklahoma, USA"
      ]
    },
    {
      "statname": "Hawaiian / PI %",
      "statval": 0.0,
      "ordinal": 24526,
      "total_in_class": 32967,
      "row_type": "ZIP",
      "ba_within_type": [
        "38077, USA",
        "88421, USA"
      ],
      "ba_overall": [
        "Hollister town, Oklahoma, USA",
        "Raber township [CCD], Hughes County, South Dakota, USA"
      ]
    },
    {
      "statname": "Other / Mixed %",
      "statval": 0.15151515151515152,
      "ordinal": 282,
      "total_in_class": 32967,
      "row_type": "ZIP",
      "ba_within_type": [
        "74434, USA",
        "90090, USA"
      ],
      "ba_overall": [
        "90090, USA",
        "DeSales University CDP, Pennsylvania, USA"
      ]
    },
    {
      "statname": "Housing Units per Adult",
      "statval": 1.3076923076923077,
      "ordinal": 676,
      "total_in_class": 32967,
      "row_type": "ZIP",
      "ba_within_type": [
        "04255, USA",
        "56524, USA"
      ],
      "ba_overall": [
        "Alatna CDP, Alaska, USA",
        "Forester township [CCD], Sanilac County, Michigan, USA"
      ]
    },
    {
      "statname": "Vacancy %",
      "statval": 0.23529411764705882,
      "ordinal": 5495,
      "total_in_class": 32967,
      "row_type": "ZIP",
      "ba_within_type": [
        "95944, USA",
        "59756, USA"
      ],
      "ba_overall": [
        "Athens township [CCD], Williams County, North Dakota, USA",
        "Logan township [CCD], Pawnee County, Kansas, USA"
      ]
    },
    {
      "statname": "2020 Presidential Election",
      "statval": -0.5319697966337826,
      "ordinal": 24095,
      "total_in_class": 32967,
      "row_type": "ZIP",
      "ba_within_type": [
        "66020, USA",
        "44618, USA"
      ],
      "ba_overall": [
        "Andrews town, North Carolina, USA",
        "Scott township [CCD], Montgomery County, Iowa, USA"
      ]
    },
    {
      "statname": "2016 Presidential Election",
      "statval": -0.4916171763117922,
      "ordinal": 23104,
      "total_in_class": 32967,
      "row_type": "ZIP",
      "ba_within_type": [
        "84338, USA",
        "63674, USA"
      ],
      "ba_overall": [
        "Winsted city, Minnesota, USA",
        "Pelion CCD [CCD], Lexington County, South Carolina, USA"
      ]
    },
    {
      "statname": "PW Density (r=250m)",
      "statval": 311.59644131155073,
      "ordinal": 22826,
      "total_in_class": 32967,
      "row_type": "ZIP",
      "ba_within_type": [
        "05759, USA",
        "45166, USA"
      ],
      "ba_overall": [
        "Benton town [CCD], Grafton County, New Hampshire, USA",
        "Sanford town, Texas, USA"
      ]
    },
    {
      "statname": "PW Density (r=500m)",
      "statval": 162.89749569308657,
      "ordinal": 20556,
      "total_in_class": 32967,
      "row_type": "ZIP",
      "ba_within_type": [
        "85646, USA",
        "26571, USA"
      ],
      "ba_overall": [
        "Murray township [CCD], Marshall County, Kansas, USA",
        "La Fayette CCD [CCD], Chambers County, Alabama, USA"
      ]
    },
    {
      "statname": "PW Density (r=2km)",
      "statval": 35.411974837946715,
      "ordinal": 21405,
      "total_in_class": 32967,
      "row_type": "ZIP",
      "ba_within_type": [
        "32658, USA",
        "17002, USA"
      ],
      "ba_overall": [
        "Puget Island CCD [CCD], Wahkiakum County, Washington, USA",
        "17002, USA"
      ]
    },
    {
      "statname": "PW Density (r=4km)",
      "statval": 43.8658754704378,
      "ordinal": 16686,
      "total_in_class": 32967,
      "row_type": "ZIP",
      "ba_within_type": [
        "04537, USA",
        "97531, USA"
      ],
      "ba_overall": [
        "04537, USA",
        "97531, USA"
      ]
    }
  ],
  "related": [
    {
      "longname": "Ohio, USA",
      "shortname": "Ohio",
      "row_type": "State"
    },
    {
      "longname": "Columbus-Marion-Zanesville CSA, OH, USA",
      "shortname": "Columbus-Marion-Zanesville CSA",
      "row_type": "CSA"
    },
    {
      "longname": "Columbus MSA, OH, USA",
      "shortname": "Columbus MSA",
      "row_type": "MSA"
    },
    {
      "longname": "Pickaway County, Ohio, USA",
      "shortname": "Pickaway County",
      "row_type": "County"
    },
    {
      "longname": "43146, USA",
      "shortname": "43146",
      "row_type": "ZIP"
    },
    {
      "longname": "Darby township [CCD], Pickaway County, Ohio, USA",
      "shortname": "Darby township",
      "row_type": "CCD"
    },
    {
      "longname": "Derby CDP, Ohio, USA",
      "shortname": "Derby CDP",
      "row_type": "City"
    }
  ]
}