{
  "shortname": "93725",
  "longname": "93725, USA",
  "source": "Census",
  "rows": [
    {
      "statname": "Population",
      "statval": 26092.0,
      "ordinal": 4664,
      "total_in_class": 32967,
      "row_type": "ZIP",
      "ba_within_type": [
        "80206, USA",
        "01803, USA"
      ],
      "ba_overall": [
        "80206, USA",
        "01803, USA"
      ]
    },
    {
      "statname": "PW Density (r=1km)",
      "statval": 1669.7768913383113,
      "ordinal": 3464,
      "total_in_class": 32967,
      "row_type": "ZIP",
      "ba_within_type": [
        "23702, USA",
        "15220, USA"
      ],
      "ba_overall": [
        "Fairview Park city [CCD], Cuyahoga County, Ohio, USA",
        "Union Park CCD [CCD], Orange County, Florida, USA"
      ]
    },
    {
      "statname": "AW Density",
      "statval": 153.58508146345415,
      "ordinal": 9895,
      "total_in_class": 32967,
      "row_type": "ZIP",
      "ba_within_type": [
        "92315, USA",
        "04105, USA"
      ],
      "ba_overall": [
        "Brodnax town, Virginia, USA",
        "Oceola township [CCD], Livingston County, Michigan, USA"
      ]
    },
    {
      "statname": "White %",
      "statval": 0.09592978690786448,
      "ordinal": 31862,
      "total_in_class": 32967,
      "row_type": "ZIP",
      "ba_within_type": [
        "85031, USA",
        "60958, USA"
      ],
      "ba_overall": [
        "Matteson village, Illinois, USA",
        "60958, USA"
      ]
    },
    {
      "statname": "Hispanic %",
      "statval": 0.6836961520772651,
      "ordinal": 757,
      "total_in_class": 32967,
      "row_type": "ZIP",
      "ba_within_type": [
        "78744, USA",
        "87507, USA"
      ],
      "ba_overall": [
        "Airport CDP, California, USA",
        "Crane city, Texas, USA"
      ]
    },
    {
      "statname": "Black %",
      "statval": 0.039590679135367166,
      "ordinal": 10203,
      "total_in_class": 32967,
      "row_type": "ZIP",
      "ba_within_type": [
        "38313, USA",
        "33455, USA"
      ],
      "ba_overall": [
        "Lincoln MSA, NE, USA",
        "Kennett Square borough [CCD], Chester County, Pennsylvania, USA"
      ]
    },
    {
      "statname": "Asian %",
      "statval": 0.15606316112218305,
      "ordinal": 1008,
      "total_in_class": 32967,
      "row_type": "ZIP",
      "ba_within_type": [
        "92630, USA",
        "60540, USA"
      ],
      "ba_overall": [
        "Milton city, Georgia, USA",
        "Davis Manor Neighborhood, Davis City, California, USA"
      ]
    },
    {
      "statname": "Native %",
      "statval": 0.004177525678368849,
      "ordinal": 9927,
      "total_in_class": 32967,
      "row_type": "ZIP",
      "ba_within_type": [
        "76053, USA",
        "30572, USA"
      ],
      "ba_overall": [
        "Marshall township [CCD], Lawrence County, Indiana, USA",
        "Denmark town [CCD], Oxford County, Maine, USA"
      ]
    },
    {
      "statname": "Hawaiian / PI %",
      "statval": 0.0010347999386785222,
      "ordinal": 4995,
      "total_in_class": 32967,
      "row_type": "ZIP",
      "ba_within_type": [
        "59758, USA",
        "71016, USA"
      ],
      "ba_overall": [
        "Kirkmansville CCD [CCD], Todd County, Kentucky, USA",
        "71016, USA"
      ]
    },
    {
      "statname": "Other / Mixed %",
      "statval": 0.01950789514027288,
      "ordinal": 29429,
      "total_in_class": 32967,
      "row_type": "ZIP",
      "ba_within_type": [
        "39051, USA",
        "39140, USA"
      ],
      "ba_overall": [
        "39051, USA",
        "Eau Pleine town [CCD], Marathon County, Wisconsin, USA"
      ]
    },
    {
      "statname": "Housing Units per Adult",
      "statval": 0.3932972731835164,
      "ordinal": 32018,
      "total_in_class": 32967,
      "row_type": "ZIP",
      "ba_within_type": [
        "99552, USA",
        "07764, USA"
      ],
      "ba_overall": [
        "Westwood Neighborhood, Lewisville City, Texas, USA",
        "07764, USA"
      ]
    },
    {
      "statname": "Vacancy %",
      "statval": 0.04437827874663264,
      "ordinal": 28797,
      "total_in_class": 32967,
      "row_type": "ZIP",
      "ba_within_type": [
        "08055, USA",
        "75132, USA"
      ],
      "ba_overall": [
        "Westhampton Neighborhood, Richmond City, Virginia, USA",
        "Callahan town, Florida, USA"
      ]
    },
    {
      "statname": "2020 Presidential Election",
      "statval": 0.3448828002293381,
      "ordinal": 4037,
      "total_in_class": 32967,
      "row_type": "ZIP",
      "ba_within_type": [
        "93060, USA",
        "38954, USA"
      ],
      "ba_overall": [
        "93060, USA",
        "38954, USA"
      ]
    },
    {
      "statname": "2016 Presidential Election",
      "statval": 0.3863187360893532,
      "ordinal": 3421,
      "total_in_class": 32967,
      "row_type": "ZIP",
      "ba_within_type": [
        "91371, USA",
        "37013, USA"
      ],
      "ba_overall": [
        "Concord city, California, USA",
        "Travis County, Texas, USA"
      ]
    },
    {
      "statname": "PW Density (r=250m)",
      "statval": 2568.19853000716,
      "ordinal": 4433,
      "total_in_class": 32967,
      "row_type": "ZIP",
      "ba_within_type": [
        "92883, USA",
        "44108, USA"
      ],
      "ba_overall": [
        "University Park Neighborhood, Jacksonville City, Florida, USA",
        "44108, USA"
      ]
    },
    {
      "statname": "PW Density (r=500m)",
      "statval": 2062.10757491932,
      "ordinal": 3345,
      "total_in_class": 32967,
      "row_type": "ZIP",
      "ba_within_type": [
        "84117, USA",
        "23608, USA"
      ],
      "ba_overall": [
        "Porter Ranch Neighborhood, Los Angeles City, California, USA",
        "Kiwanis Park Neighborhood, Tempe City, Arizona, USA"
      ]
    },
    {
      "statname": "PW Density (r=2km)",
      "statval": 1277.9966104691482,
      "ordinal": 3940,
      "total_in_class": 32967,
      "row_type": "ZIP",
      "ba_within_type": [
        "07721, USA",
        "60073, USA"
      ],
      "ba_overall": [
        "Detroit-Warren-Dearborn MSA, MI, USA",
        "Pacheco CDP, California, USA"
      ]
    },
    {
      "statname": "PW Density (r=4km)",
      "statval": 1107.9891333888193,
      "ordinal": 3842,
      "total_in_class": 32967,
      "row_type": "ZIP",
      "ba_within_type": [
        "30008, USA",
        "75057, USA"
      ],
      "ba_overall": [
        "Village Woods Neighborhood, Fort Wayne City, Indiana, USA",
        "West Greenville Neighborhood, Greenville City, South Carolina, USA"
      ]
    }
  ],
  "related": {
    "same_geography": [],
    "contained_by": [],
    "contains": [
      {
        "longname": "Bowles CDP, California, USA",
        "shortname": "Bowles CDP",
        "row_type": "City"
      },
      {
        "longname": "Calwa CDP, California, USA",
        "shortname": "Calwa CDP",
        "row_type": "City"
      },
      {
        "longname": "Malaga CDP, California, USA",
        "shortname": "Malaga CDP",
        "row_type": "City"
      },
      {
        "longname": "Monmouth CDP, California, USA",
        "shortname": "Monmouth CDP",
        "row_type": "City"
      }
    ],
    "borders": [
      {
        "longname": "93242, USA",
        "shortname": "93242",
        "row_type": "ZIP"
      },
      {
        "longname": "93609, USA",
        "shortname": "93609",
        "row_type": "ZIP"
      },
      {
        "longname": "93616, USA",
        "shortname": "93616",
        "row_type": "ZIP"
      },
      {
        "longname": "93625, USA",
        "shortname": "93625",
        "row_type": "ZIP"
      },
      {
        "longname": "93657, USA",
        "shortname": "93657",
        "row_type": "ZIP"
      },
      {
        "longname": "93662, USA",
        "shortname": "93662",
        "row_type": "ZIP"
      },
      {
        "longname": "93702, USA",
        "shortname": "93702",
        "row_type": "ZIP"
      },
      {
        "longname": "93706, USA",
        "shortname": "93706",
        "row_type": "ZIP"
      },
      {
        "longname": "93721, USA",
        "shortname": "93721",
        "row_type": "ZIP"
      },
      {
        "longname": "93727, USA",
        "shortname": "93727",
        "row_type": "ZIP"
      }
    ],
    "intersects": [
      {
        "longname": "Edison Neighborhood, Fresno City, California, USA",
        "shortname": "Edison, Fresno",
        "row_type": "Neighborhood"
      },
      {
        "longname": "Roosevelt Neighborhood, Fresno City, California, USA",
        "shortname": "Roosevelt, Fresno",
        "row_type": "Neighborhood"
      }
    ]
  }
}