{
  "shortname": "Lively Grove township",
  "longname": "Lively Grove township [CCD], Washington County, Illinois, USA",
  "source": "Census",
  "rows": [
    {
      "statname": "Population",
      "statval": 550.0,
      "ordinal": 25240,
      "total_in_class": 36301,
      "row_type": "CCD",
      "ba_within_type": [
        "Franklin township [CCD], Columbia County, Pennsylvania, USA",
        "Starr township [CCD], Cloud County, Kansas, USA"
      ],
      "ba_overall": [
        "98830, USA",
        "San Juan del Centro Neighborhood, Boulder City, Colorado, USA"
      ]
    },
    {
      "statname": "PW Density (r=1km)",
      "statval": 16.40627027916018,
      "ordinal": 26880,
      "total_in_class": 36301,
      "row_type": "CCD",
      "ba_within_type": [
        "Rosedale township [CCD], Jersey County, Illinois, USA",
        "Leonidas township [CCD], St. Joseph County, Michigan, USA"
      ],
      "ba_overall": [
        "Rosedale township [CCD], Jersey County, Illinois, USA",
        "93641, USA"
      ]
    },
    {
      "statname": "AW Density",
      "statval": 5.902910622987321,
      "ordinal": 25001,
      "total_in_class": 36301,
      "row_type": "CCD",
      "ba_within_type": [
        "Lawton city [CCD], Ramsey County, North Dakota, USA",
        "Larkinsburg township [CCD], Clay County, Illinois, USA"
      ],
      "ba_overall": [
        "76252, USA",
        "Three Lakes School District, Wisconsin, USA"
      ]
    },
    {
      "statname": "White %",
      "statval": 0.9672727272727273,
      "ordinal": 3096,
      "total_in_class": 36301,
      "row_type": "CCD",
      "ba_within_type": [
        "La Harpe township [CCD], Hancock County, Illinois, USA",
        "Raglan township [CCD], Harrison County, Iowa, USA"
      ],
      "ba_overall": [
        "Tell township [CCD], Huntingdon County, Pennsylvania, USA",
        "Raglan township [CCD], Harrison County, Iowa, USA"
      ]
    },
    {
      "statname": "Hispanic %",
      "statval": 0.007272727272727273,
      "ordinal": 31550,
      "total_in_class": 36301,
      "row_type": "CCD",
      "ba_within_type": [
        "Johnson township [CCD], Knox County, Indiana, USA",
        "Freedom township [CCD], Adams County, Pennsylvania, USA"
      ],
      "ba_overall": [
        "Olanta town, South Carolina, USA",
        "Hall Elementary School District, Montana, USA"
      ]
    },
    {
      "statname": "Black %",
      "statval": 0.0,
      "ordinal": 31601,
      "total_in_class": 36301,
      "row_type": "CCD",
      "ba_within_type": [
        "Sterling town [CCD], Vernon County, Wisconsin, USA",
        "Franklin township [CCD], Columbia County, Pennsylvania, USA"
      ],
      "ba_overall": [
        "Carrizo Hill CDP, Texas, USA",
        "Good Thunder city, Minnesota, USA"
      ]
    },
    {
      "statname": "Asian %",
      "statval": 0.0036363636363636364,
      "ordinal": 16605,
      "total_in_class": 36301,
      "row_type": "CCD",
      "ba_within_type": [
        "Pinckneyville No. 6 precinct [CCD], Perry County, Illinois, USA",
        "Valley township [CCD], Stark County, Illinois, USA"
      ],
      "ba_overall": [
        "Clayton village [CCD], Polk County, Wisconsin, USA",
        "Pinckneyville No. 6 precinct [CCD], Perry County, Illinois, USA"
      ]
    },
    {
      "statname": "Native %",
      "statval": 0.0,
      "ordinal": 31204,
      "total_in_class": 36301,
      "row_type": "CCD",
      "ba_within_type": [
        "Clear Creek township [CCD], Drew County, Arkansas, USA",
        "Malcom township [CCD], Poweshiek County, Iowa, USA"
      ],
      "ba_overall": [
        "Cherry Tree borough, Pennsylvania, USA",
        "Stapleton village, Nebraska, USA"
      ]
    },
    {
      "statname": "Hawaiian / PI %",
      "statval": 0.0,
      "ordinal": 23987,
      "total_in_class": 36301,
      "row_type": "CCD",
      "ba_within_type": [
        "Sterling town [CCD], Vernon County, Wisconsin, USA",
        "Starr township [CCD], Cloud County, Kansas, USA"
      ],
      "ba_overall": [
        "San Juan del Centro Neighborhood, Boulder City, Colorado, USA",
        "98830, USA"
      ]
    },
    {
      "statname": "Other / Mixed %",
      "statval": 0.02181818181818182,
      "ordinal": 28263,
      "total_in_class": 36301,
      "row_type": "CCD",
      "ba_within_type": [
        "Sterling town [CCD], Vernon County, Wisconsin, USA",
        "Paterson city [CCD], Passaic County, New Jersey, USA"
      ],
      "ba_overall": [
        "Stonington town [CCD], Hancock County, Maine, USA",
        "Seneca School District, Wisconsin, USA"
      ]
    },
    {
      "statname": "Housing Units per Adult",
      "statval": 0.5639913232104121,
      "ordinal": 19888,
      "total_in_class": 36301,
      "row_type": "CCD",
      "ba_within_type": [
        "York township [CCD], Switzerland County, Indiana, USA",
        "Jefferson township [CCD], Saline County, Arkansas, USA"
      ],
      "ba_overall": [
        "Tidmore Bend CDP, Alabama, USA",
        "33982, USA"
      ]
    },
    {
      "statname": "Vacancy %",
      "statval": 0.07692307692307693,
      "ordinal": 24922,
      "total_in_class": 36301,
      "row_type": "CCD",
      "ba_within_type": [
        "St. Andrews township [CCD], Walsh County, North Dakota, USA",
        "Poweshiek township [CCD], Jasper County, Iowa, USA"
      ],
      "ba_overall": [
        "Ogeecheeton/Dawes Avenue Neighborhood, Savannah City, Georgia, USA",
        "Wilbur township [CCD], Brule County, South Dakota, USA"
      ]
    },
    {
      "statname": "2020 Presidential Election",
      "statval": -0.5964912280701754,
      "ordinal": 26573,
      "total_in_class": 36301,
      "row_type": "CCD",
      "ba_within_type": [
        "Coldwater township [CCD], Cross County, Arkansas, USA",
        "Alexander town [CCD], Genesee County, New York, USA"
      ],
      "ba_overall": [
        "District 6 [CCD], Lauderdale County, Tennessee, USA",
        "Coldwater township [CCD], Cross County, Arkansas, USA"
      ]
    },
    {
      "statname": "2016 Presidential Election",
      "statval": -0.5674846625766872,
      "ordinal": 26045,
      "total_in_class": 36301,
      "row_type": "CCD",
      "ba_within_type": [
        "Green township [CCD], Gallia County, Ohio, USA",
        "Optimus township [CCD], Stone County, Arkansas, USA"
      ],
      "ba_overall": [
        "LA-SD026, USA",
        "Optimus township [CCD], Stone County, Arkansas, USA"
      ]
    },
    {
      "statname": "PW Density (r=250m)",
      "statval": 110.43385316735673,
      "ordinal": 28841,
      "total_in_class": 36301,
      "row_type": "CCD",
      "ba_within_type": [
        "Aurora town [CCD], Taylor County, Wisconsin, USA",
        "Elk Fork township [CCD], Pettis County, Missouri, USA"
      ],
      "ba_overall": [
        "Aurora town [CCD], Taylor County, Wisconsin, USA",
        "LaGrange town, Arkansas, USA"
      ]
    },
    {
      "statname": "PW Density (r=500m)",
      "statval": 38.822231209470324,
      "ordinal": 27706,
      "total_in_class": 36301,
      "row_type": "CCD",
      "ba_within_type": [
        "Minneola township [CCD], Goodhue County, Minnesota, USA",
        "Elba city [CCD], Winona County, Minnesota, USA"
      ],
      "ba_overall": [
        "Lowell Point CDP, Alaska, USA",
        "Elba city [CCD], Winona County, Minnesota, USA"
      ]
    },
    {
      "statname": "PW Density (r=2km)",
      "statval": 17.58937025158057,
      "ordinal": 23451,
      "total_in_class": 36301,
      "row_type": "CCD",
      "ba_within_type": [
        "Chestnut Hill township [CCD], Ashe County, North Carolina, USA",
        "Valley township [CCD], Ouachita County, Arkansas, USA"
      ],
      "ba_overall": [
        "93255, USA",
        "Valley township [CCD], Ouachita County, Arkansas, USA"
      ]
    },
    {
      "statname": "PW Density (r=4km)",
      "statval": 11.30473943623935,
      "ordinal": 24427,
      "total_in_class": 36301,
      "row_type": "CCD",
      "ba_within_type": [
        "Elmwood township [CCD], Tuscola County, Michigan, USA",
        "Bois Brule township [CCD], Perry County, Missouri, USA"
      ],
      "ba_overall": [
        "Elmwood township [CCD], Tuscola County, Michigan, USA",
        "14024, USA"
      ]
    }
  ],
  "related": {
    "same_geography": [],
    "contained_by": [
      {
        "longname": "Illinois, USA",
        "shortname": "Illinois",
        "row_type": "State"
      },
      {
        "longname": "Washington County, Illinois, USA",
        "shortname": "Washington County",
        "row_type": "County"
      },
      {
        "longname": "Historical Congressional District IL-15, 113th-117th Congress, USA",
        "shortname": "IL-15 [113th-117th Congress]",
        "row_type": "Historical Congressional District"
      },
      {
        "longname": "Historical Congressional District IL-19, 108th-112th Congress, USA",
        "shortname": "IL-19 [108th-112th Congress]",
        "row_type": "Historical Congressional District"
      },
      {
        "longname": "Historical Congressional District IL-20, 103rd-107th Congress, USA",
        "shortname": "IL-20 [103rd-107th Congress]",
        "row_type": "Historical Congressional District"
      },
      {
        "longname": "Historical Congressional District IL-22, 98th-102nd Congress, USA",
        "shortname": "IL-22 [98th-102nd Congress]",
        "row_type": "Historical Congressional District"
      },
      {
        "longname": "Historical Congressional District IL-24, 93rd-97th Congress, USA",
        "shortname": "IL-24 [93rd-97th Congress]",
        "row_type": "Historical Congressional District"
      },
      {
        "longname": "Historical Congressional District IL-21, 90th-92nd Congress, USA",
        "shortname": "IL-21 [90th-92nd Congress]",
        "row_type": "Historical Congressional District"
      },
      {
        "longname": "Historical Congressional District IL-23, 88th-89th Congress, USA",
        "shortname": "IL-23 [88th-89th Congress]",
        "row_type": "Historical Congressional District"
      },
      {
        "longname": "Historical Congressional District IL-23, 83rd-87th Congress, USA",
        "shortname": "IL-23 [83rd-87th Congress]",
        "row_type": "Historical Congressional District"
      },
      {
        "longname": "Historical Congressional District IL-24, 81st-82nd Congress, USA",
        "shortname": "IL-24 [81st-82nd Congress]",
        "row_type": "Historical Congressional District"
      },
      {
        "longname": "Historical Congressional District IL-22, 78th-80th Congress, USA",
        "shortname": "IL-22 [78th-80th Congress]",
        "row_type": "Historical Congressional District"
      },
      {
        "longname": "Historical Congressional District IL-22, 63rd-77th Congress, USA",
        "shortname": "IL-22 [63rd-77th Congress]",
        "row_type": "Historical Congressional District"
      },
      {
        "longname": "Historical Congressional District IL-22, 58th-62nd Congress, USA",
        "shortname": "IL-22 [58th-62nd Congress]",
        "row_type": "Historical Congressional District"
      },
      {
        "longname": "Historical Congressional District IL-21, 54th-57th Congress, USA",
        "shortname": "IL-21 [54th-57th Congress]",
        "row_type": "Historical Congressional District"
      },
      {
        "longname": "Historical Congressional District IL-18, 53rd Congress, USA",
        "shortname": "IL-18 [53rd Congress]",
        "row_type": "Historical Congressional District"
      },
      {
        "longname": "Historical Congressional District IL-18, 48th-52nd Congress, USA",
        "shortname": "IL-18 [48th-52nd Congress]",
        "row_type": "Historical Congressional District"
      },
      {
        "longname": "Historical Congressional District IL-16, 43rd-47th Congress, USA",
        "shortname": "IL-16 [43rd-47th Congress]",
        "row_type": "Historical Congressional District"
      },
      {
        "longname": "Historical Congressional District IL-12, 38th-42nd Congress, USA",
        "shortname": "IL-12 [38th-42nd Congress]",
        "row_type": "Historical Congressional District"
      },
      {
        "longname": "Historical Congressional District IL-8, 33rd-37th Congress, USA",
        "shortname": "IL-08 [33rd-37th Congress]",
        "row_type": "Historical Congressional District"
      },
      {
        "longname": "Historical Congressional District IL-1, 28th-32nd Congress, USA",
        "shortname": "IL-01 [28th-32nd Congress]",
        "row_type": "Historical Congressional District"
      },
      {
        "longname": "Historical Congressional District IL-1, 23rd-27th Congress, USA",
        "shortname": "IL-01 [23rd-27th Congress]",
        "row_type": "Historical Congressional District"
      },
      {
        "longname": "IL-HD115, USA",
        "shortname": "IL-HD115",
        "row_type": "State House District"
      },
      {
        "longname": "IL-SD058, USA",
        "shortname": "IL-SD058",
        "row_type": "State Senate District"
      },
      {
        "longname": "IL-12, USA",
        "shortname": "IL-12",
        "row_type": "Congressional District"
      }
    ],
    "contains": [],
    "borders": [
      {
        "longname": "Coulterville precinct [CCD], Randolph County, Illinois, USA",
        "shortname": "Coulterville precinct",
        "row_type": "CCD"
      },
      {
        "longname": "Johannisburg township [CCD], Washington County, Illinois, USA",
        "shortname": "Johannisburg township",
        "row_type": "CCD"
      },
      {
        "longname": "Marissa township [CCD], St. Clair County, Illinois, USA",
        "shortname": "Marissa township",
        "row_type": "CCD"
      },
      {
        "longname": "Oakdale township [CCD], Washington County, Illinois, USA",
        "shortname": "Oakdale township",
        "row_type": "CCD"
      },
      {
        "longname": "Plum Hill township [CCD], Washington County, Illinois, USA",
        "shortname": "Plum Hill township",
        "row_type": "CCD"
      },
      {
        "longname": "Swanwick precinct [CCD], Perry County, Illinois, USA",
        "shortname": "Swanwick precinct",
        "row_type": "CCD"
      },
      {
        "longname": "Tilden precinct [CCD], Randolph County, Illinois, USA",
        "shortname": "Tilden precinct",
        "row_type": "CCD"
      },
      {
        "longname": "Tilden village, Illinois, USA",
        "shortname": "Tilden village",
        "row_type": "City"
      },
      {
        "longname": "Coulterville Unit School District 1, Illinois, USA",
        "shortname": "Coulterville Unit School District 1",
        "row_type": "School District"
      },
      {
        "longname": "Nashville Community High School District 99, Illinois, USA",
        "shortname": "Nashville Community High School District 99",
        "row_type": "School District"
      },
      {
        "longname": "Oakdale Community Consolidated School District 1, Illinois, USA",
        "shortname": "Oakdale Community Consolidated School District 1",
        "row_type": "School District"
      },
      {
        "longname": "Pinckneyville Community High School District 101, Illinois, USA",
        "shortname": "Pinckneyville Community High School District 101",
        "row_type": "School District"
      },
      {
        "longname": "Pinckneyville School District 50, Illinois, USA",
        "shortname": "Pinckneyville School District 50",
        "row_type": "School District"
      },
      {
        "longname": "Sparta Community Unit School District 140, Illinois, USA",
        "shortname": "Sparta Community Unit School District 140",
        "row_type": "School District"
      }
    ],
    "intersects": [
      {
        "longname": "Marissa Community Unit School District 40, Illinois, USA",
        "shortname": "Marissa Community Unit School District 40",
        "row_type": "School District"
      },
      {
        "longname": "West Washington County Community Unit District 10, Illinois, USA",
        "shortname": "West Washington County Community Unit District 10",
        "row_type": "School District"
      }
    ]
  }
}