{
  "shortname": "Six Shooter Canyon CDP",
  "longname": "Six Shooter Canyon CDP, Arizona, USA",
  "source": "Census",
  "rows": [
    {
      "statname": "Population",
      "statval": 958.0,
      "ordinal": 15081,
      "total_in_class": 29168,
      "row_type": "City",
      "ba_within_type": [
        "New London city, Texas, USA",
        "Hilltop city, Minnesota, USA"
      ],
      "ba_overall": [
        "Hilltop city [CCD], Anoka County, Minnesota, USA",
        "55990, USA"
      ]
    },
    {
      "statname": "PW Density (r=1km)",
      "statval": 242.43716957620342,
      "ordinal": 13770,
      "total_in_class": 29168,
      "row_type": "City",
      "ba_within_type": [
        "Cissna Park village, Illinois, USA",
        "Clanton city, Alabama, USA"
      ],
      "ba_overall": [
        "Jones County, Mississippi, USA",
        "Clanton city, Alabama, USA"
      ]
    },
    {
      "statname": "AW Density",
      "statval": 126.80926752482132,
      "ordinal": 20930,
      "total_in_class": 29168,
      "row_type": "City",
      "ba_within_type": [
        "Altheimer city, Arkansas, USA",
        "Flovilla city, Georgia, USA"
      ],
      "ba_overall": [
        "Altheimer city, Arkansas, USA",
        "Flovilla city, Georgia, USA"
      ]
    },
    {
      "statname": "White %",
      "statval": 0.6325678496868476,
      "ordinal": 21756,
      "total_in_class": 29168,
      "row_type": "City",
      "ba_within_type": [
        "Sims town, North Carolina, USA",
        "River Falls town, Alabama, USA"
      ],
      "ba_overall": [
        "River Falls town, Alabama, USA",
        "77442, USA"
      ]
    },
    {
      "statname": "Hispanic %",
      "statval": 0.29331941544885176,
      "ordinal": 2871,
      "total_in_class": 29168,
      "row_type": "City",
      "ba_within_type": [
        "Monticello village, New York, USA",
        "San Leanna village, Texas, USA"
      ],
      "ba_overall": [
        "22204, USA",
        "33510, USA"
      ]
    },
    {
      "statname": "Black %",
      "statval": 0.0041753653444676405,
      "ordinal": 18938,
      "total_in_class": 29168,
      "row_type": "City",
      "ba_within_type": [
        "Hospers city, Iowa, USA",
        "San Jose village, Illinois, USA"
      ],
      "ba_overall": [
        "68340, USA",
        "Liberty township [CCD], Van Wert County, Ohio, USA"
      ]
    },
    {
      "statname": "Asian %",
      "statval": 0.0041753653444676405,
      "ordinal": 15831,
      "total_in_class": 29168,
      "row_type": "City",
      "ba_within_type": [
        "Edneyville CDP, North Carolina, USA",
        "Briarcliffe Acres town, South Carolina, USA"
      ],
      "ba_overall": [
        "Orangeville borough, Pennsylvania, USA",
        "32621, USA"
      ]
    },
    {
      "statname": "Native %",
      "statval": 0.027139874739039668,
      "ordinal": 2423,
      "total_in_class": 29168,
      "row_type": "City",
      "ba_within_type": [
        "Escanaba city, Michigan, USA",
        "Liberty village, Nebraska, USA"
      ],
      "ba_overall": [
        "Escanaba city, Michigan, USA",
        "Buckingham Neighborhood, Fort Collins City, Colorado, USA"
      ]
    },
    {
      "statname": "Hawaiian / PI %",
      "statval": 0.0,
      "ordinal": 19784,
      "total_in_class": 29168,
      "row_type": "City",
      "ba_within_type": [
        "Walker city, Minnesota, USA",
        "Hilltop city, Minnesota, USA"
      ],
      "ba_overall": [
        "Hilltop city [CCD], Anoka County, Minnesota, USA",
        "55990, USA"
      ]
    },
    {
      "statname": "Other / Mixed %",
      "statval": 0.038622129436325675,
      "ordinal": 15778,
      "total_in_class": 29168,
      "row_type": "City",
      "ba_within_type": [
        "Lake Park city, Georgia, USA",
        "Amenia CDP, New York, USA"
      ],
      "ba_overall": [
        "Jefferson township [CCD], Tuscarawas County, Ohio, USA",
        "Amenia CDP, New York, USA"
      ]
    },
    {
      "statname": "Housing Units per Adult",
      "statval": 0.6065573770491803,
      "ordinal": 11994,
      "total_in_class": 29168,
      "row_type": "City",
      "ba_within_type": [
        "Otoe village, Nebraska, USA",
        "Annex CDP, Oregon, USA"
      ],
      "ba_overall": [
        "Otoe village, Nebraska, USA",
        "Maple Grove precinct [CCD], Johnson County, Nebraska, USA"
      ]
    },
    {
      "statname": "Vacancy %",
      "statval": 0.13288288288288289,
      "ordinal": 10411,
      "total_in_class": 29168,
      "row_type": "City",
      "ba_within_type": [
        "Brownville village, New York, USA",
        "Chamberlain city, South Dakota, USA"
      ],
      "ba_overall": [
        "Warrensburg city, Missouri, USA",
        "Long Creek township [CCD], Boone County, Arkansas, USA"
      ]
    },
    {
      "statname": "2020 Presidential Election",
      "statval": -0.41986062717770045,
      "ordinal": 18041,
      "total_in_class": 29168,
      "row_type": "City",
      "ba_within_type": [
        "Coloma village, Wisconsin, USA",
        "Northrop city, Minnesota, USA"
      ],
      "ba_overall": [
        "Carteret County, North Carolina, USA",
        "Northrop city, Minnesota, USA"
      ]
    },
    {
      "statname": "2016 Presidential Election",
      "statval": -0.44787644787644776,
      "ordinal": 19292,
      "total_in_class": 29168,
      "row_type": "City",
      "ba_within_type": [
        "Chadwick village, Illinois, USA",
        "Hanover village, Michigan, USA"
      ],
      "ba_overall": [
        "Chadwick village, Illinois, USA",
        "Hanover village, Michigan, USA"
      ]
    },
    {
      "statname": "PW Density (r=250m)",
      "statval": 1185.521580275329,
      "ordinal": 8786,
      "total_in_class": 29168,
      "row_type": "City",
      "ba_within_type": [
        "South Willard CDP, Utah, USA",
        "Clinton village, Michigan, USA"
      ],
      "ba_overall": [
        "South Willard CDP, Utah, USA",
        "District 4 [CCD], Tunica County, Mississippi, USA"
      ]
    },
    {
      "statname": "PW Density (r=500m)",
      "statval": 351.52708445264864,
      "ordinal": 15383,
      "total_in_class": 29168,
      "row_type": "City",
      "ba_within_type": [
        "Walnut Creek CDP, Ohio, USA",
        "Danville city, Arkansas, USA"
      ],
      "ba_overall": [
        "82334, USA",
        "68638, USA"
      ]
    },
    {
      "statname": "PW Density (r=2km)",
      "statval": 140.18576714494785,
      "ordinal": 12996,
      "total_in_class": 29168,
      "row_type": "City",
      "ba_within_type": [
        "Fort Recovery village, Ohio, USA",
        "Gurdon city, Arkansas, USA"
      ],
      "ba_overall": [
        "Fort Recovery village, Ohio, USA",
        "74010, USA"
      ]
    },
    {
      "statname": "PW Density (r=4km)",
      "statval": 127.64292888973387,
      "ordinal": 10219,
      "total_in_class": 29168,
      "row_type": "City",
      "ba_within_type": [
        "Larose CDP, Louisiana, USA",
        "Edna city, Texas, USA"
      ],
      "ba_overall": [
        "Larose CDP, Louisiana, USA",
        "Edna city, Texas, USA"
      ]
    }
  ],
  "related": [
    {
      "longname": "Arizona, USA",
      "shortname": "Arizona",
      "row_type": "State"
    },
    {
      "longname": "Gila County, Arizona, USA",
      "shortname": "Gila County",
      "row_type": "County"
    },
    {
      "longname": "Payson MSA, AZ, USA",
      "shortname": "Payson MSA",
      "row_type": "MSA"
    },
    {
      "longname": "Globe-Miami CCD [CCD], Gila County, Arizona, USA",
      "shortname": "Globe-Miami CCD",
      "row_type": "CCD"
    },
    {
      "longname": "Globe city, Arizona, USA",
      "shortname": "Globe city",
      "row_type": "City"
    },
    {
      "longname": "Icehouse Canyon CDP, Arizona, USA",
      "shortname": "Icehouse Canyon CDP",
      "row_type": "City"
    }
  ]
}